jhpbar/__init__.py
jhpbar/pbar.py
jhpbar-1.2.2.dist-info/METADATA
jhpbar-1.2.2.dist-info/WHEEL
jhpbar-1.2.2.dist-info/top_level.txt
jhpbar-1.2.2.dist-info/RECORD
