Metadata-Version: 2.1
Name: jhpbar
Version: 1.2.2
Summary: custom progress bar bug fix
Home-page: https://github.com/jhkim31/jh-pbar
Author: jh.kim
Author-email: biz.jh.kim@gmail.com
License: UNKNOWN
Keywords: progress_bar
Platform: UNKNOWN
Classifier: Programming Language :: Python :: 3
Classifier: Programming Language :: Python :: 3.2
Classifier: Programming Language :: Python :: 3.3
Classifier: Programming Language :: Python :: 3.4
Classifier: Programming Language :: Python :: 3.5
Classifier: Programming Language :: Python :: 3.6
Classifier: Programming Language :: Python :: 3.7
Requires-Python: >=3
